{
 "login": "BloodFire",
 "password": "¨©ª«¬­®¯",
 "email": "wekeva8417@funboxcn.com",
 "ConfirmationMail": true,
 "moder": false,
 "avatar": "64457169148e24d4a675c7178c93cd66",
 "friends": [
  {
   "login": "Ren4L"
  }
 ],
 "applications": [],
 "sendApplications": [],
 "firstName": "Anton",
 "lastName": "Rodin",
 "gender": "Male",
 "date": "2003-01-29",
 "country": "Беларусь",
 "city": "Брест",
 "visibility": "Everything",
 "Posts": [
  {
   "date": 1637065468469,
   "content": "Издание Ars Technica обратило внимание на перечень изменений в новой версии инсайдерской сборки Windows 11, где отмечается, что «чёрный экран смерти» сменит цвет на каноничный синий.\nПоскольку Microsoft не делала никаких анонсов, можно лишь предположить, что компания позиционировала свежую ОС как нечто, дающее новый опыт буквально во всём. Поэтому решила заменить даже привычный для многих элемент, хотя впоследствии передумала.\nРелиз Windows 11 не обошёлся без проблем — в сети то и дело появляются сообщения об очередных багах, но создатели ОС стараются исправлять их оперативно по мере возможностей. Хватает, впрочем, и позитивных вещей — например, в некоторых играх незначительно выросла производительность."
  }
 ],
 "Videos": [
  "47af09ff0a1b7040b6e2abd6cd716607"
 ],
 "Photos": [
  "797c44e32f61d77655397157359721ef"
 ]
}